RPA/Dialogs/__init__.py
RPA/Dialogs/dialog.py
RPA/Dialogs/dialog_types.py
RPA/Dialogs/library.py
RPA/Dialogs/utils.py
rpaframework_dialogs-4.0.5.dist-info/LICENSE
rpaframework_dialogs-4.0.5.dist-info/METADATA
rpaframework_dialogs-4.0.5.dist-info/WHEEL
rpaframework_dialogs-4.0.5.dist-info/RECORD
