Metadata-Version: 2.1
Name: rpaframework-dialogs
Version: 4.0.5
Summary: Dialogs library of RPA Framework
Home-page: https://rpaframework.org/
License: Apache-2.0
Keywords: robotframework,rpa,automation,dialogs
Author: RPA Framework
Author-email: rpafw@robocorp.com
Requires-Python: >=3.8,<4.0
Classifier: Development Status :: 5 - Production/Stable
Classifier: Framework :: Robot Framework
Classifier: Framework :: Robot Framework :: Library
Classifier: Intended Audience :: Developers
Classifier: License :: OSI Approved :: Apache Software License
Classifier: Operating System :: OS Independent
Classifier: Programming Language :: Python :: 3
Classifier: Programming Language :: Python :: 3.8
Classifier: Programming Language :: Python :: 3.9
Classifier: Programming Language :: Python :: 3.10
Classifier: Programming Language :: Python :: 3.11
Classifier: Topic :: Software Development :: Libraries
Classifier: Topic :: Software Development :: Libraries :: Python Modules
Requires-Dist: robocorp-dialog (>=0.5.3,<0.6.0)
Requires-Dist: robotframework (>=4.0.0,!=4.0.1,<6.0.0)
Requires-Dist: rpaframework-core (>=11.0.0,<12.0.0)
Project-URL: Documentation, https://rpaframework.org/
Project-URL: Repository, https://github.com/robocorp/rpaframework
